{"45degreee_fabric.png":"textures/45degreee_fabric.png","60degree_gray.png":"textures/60degree_gray.png","absurdidad.png":"textures/absurdidad.png","agsquare.png":"textures/agsquare.png","always_grey.png":"textures/always_grey.png","arab_tile.png":"textures/arab_tile.png","arches.png":"textures/arches.png","argyle.png":"textures/argyle.png","asfalt.png":"textures/asfalt.png","assault.png":"textures/assault.png","az_subtle.png":"textures/az_subtle.png","back_pattern.png":"textures/back_pattern.png","batthern.png":"textures/batthern.png","bedge_grunge.png":"textures/bedge_grunge.png","beige_paper.png":"textures/beige_paper.png","bgnoise_lg.png":"textures/bgnoise_lg.png","billie_holiday.png":"textures/billie_holiday.png","binding_dark.png":"textures/binding_dark.png","binding_light.png":"textures/binding_light.png","black-Linen.png":"textures/black-Linen.png","black_denim.png":"textures/black_denim.png","black_linen_v2.png":"textures/black_linen_v2.png","black_lozenge.png":"textures/black_lozenge.png","black_mamba.png":"textures/black_mamba.png","black_paper.png":"textures/black_paper.png","black_scales.png":"textures/black_scales.png","black_thread.png":"textures/black_thread.png","black_twill.png":"textures/black_twill.png","blackmamba.png":"textures/blackmamba.png","blackorchid.png":"textures/blackorchid.png","blizzard.png":"textures/blizzard.png","blu_stripes.png":"textures/blu_stripes.png","bo_play_pattern.png":"textures/bo_play_pattern.png","brickwall.png":"textures/brickwall.png","bright_squares.png":"textures/bright_squares.png","brillant.png":"textures/brillant.png","broken_noise.png":"textures/broken_noise.png","brushed_alu.png":"textures/brushed_alu.png","brushed_alu_dark.png":"textures/brushed_alu_dark.png","burried.png":"textures/burried.png","candyhole.png":"textures/candyhole.png","carbon_fibre.png":"textures/carbon_fibre.png","carbon_fibre_big.png":"textures/carbon_fibre_big.png","carbon_fibre_v2.png":"textures/carbon_fibre_v2.png","cardboard.png":"textures/cardboard.png","cardboard_1.png":"textures/cardboard_1.png","cardboard_flat.png":"textures/cardboard_flat.png","cartographer.png":"textures/cartographer.png","checkered_pattern.png":"textures/checkered_pattern.png","chruch.png":"textures/chruch.png","circles.png":"textures/circles.png","classy_fabric.png":"textures/classy_fabric.png","clean_textile.png":"textures/clean_textile.png","climpek.png":"textures/climpek.png","cloth_alike.png":"textures/cloth_alike.png","concrete_wall.png":"textures/concrete_wall.png","concrete_wall_2.png":"textures/concrete_wall_2.png","concrete_wall_3.png":"textures/concrete_wall_3.png","connect.png":"textures/connect.png","cork_1.png":"textures/cork_1.png","corrugation.png":"textures/corrugation.png","cracks_1.png":"textures/cracks_1.png","cream_dust.png":"textures/cream_dust.png","cream_pixels.png":"textures/cream_pixels.png","creampaper.png":"textures/creampaper.png","crisp_paper_ruffles.png":"textures/crisp_paper_ruffles.png","crissXcross.png":"textures/crissXcross.png","cross_scratches.png":"textures/cross_scratches.png","crossed_stripes.png":"textures/crossed_stripes.png","crosses.png":"textures/crosses.png","cubes.png":"textures/cubes.png","cutcube.png":"textures/cutcube.png","daimond_eyes.png":"textures/daimond_eyes.png","dark_brick_wall.png":"textures/dark_brick_wall.png","dark_circles.png":"textures/dark_circles.png","dark_dotted.png":"textures/dark_dotted.png","dark_dotted2.png":"textures/dark_dotted2.png","dark_exa.png":"textures/dark_exa.png","dark_fish_skin.png":"textures/dark_fish_skin.png","dark_geometric.png":"textures/dark_geometric.png","dark_leather.png":"textures/dark_leather.png","dark_matter.png":"textures/dark_matter.png","dark_mosaic.png":"textures/dark_mosaic.png","dark_stripes.png":"textures/dark_stripes.png","dark_Tire.png":"textures/dark_Tire.png","dark_wall.png":"textures/dark_wall.png","dark_wood.png":"textures/dark_wood.png","darkdenim3.png":"textures/darkdenim3.png","darth_stripe.png":"textures/darth_stripe.png","debut_dark.png":"textures/debut_dark.png","debut_light.png":"textures/debut_light.png","denim.png":"textures/denim.png","diagmonds.png":"textures/diagmonds.png","diagonal-noise.png":"textures/diagonal-noise.png","diagonal_striped_brick.png":"textures/diagonal_striped_brick.png","diagonal_waves.png":"textures/diagonal_waves.png","diagonales_decalees.png":"textures/diagonales_decalees.png","diamond_upholstery.png":"textures/diamond_upholstery.png","diamonds.png":"textures/diamonds.png","dirty_old_shirt.png":"textures/dirty_old_shirt.png","double_lined.png":"textures/double_lined.png","dust.png":"textures/dust.png","dvsup.png":"textures/dvsup.png","ecailles.png":"textures/ecailles.png","egg_shell.png":"textures/egg_shell.png","elastoplast.png":"textures/elastoplast.png","elegant_grid.png":"textures/elegant_grid.png","embossed_paper.png":"textures/embossed_paper.png","escheresque.png":"textures/escheresque.png","escheresque_ste.png":"textures/escheresque_ste.png","exclusive_paper.png":"textures/exclusive_paper.png","extra_clean_paper.png":"textures/extra_clean_paper.png","fabric_1.png":"textures/fabric_1.png","fabric_of_squares_gray.png":"textures/fabric_of_squares_gray.png","fabric_plaid.png":"textures/fabric_plaid.png","fake_brick.png":"textures/fake_brick.png","fake_luxury.png":"textures/fake_luxury.png","fancy_deboss.png":"textures/fancy_deboss.png","farmer.png":"textures/farmer.png","felt.png":"textures/felt.png","first_aid_kit.png":"textures/first_aid_kit.png","flowers.png":"textures/flowers.png","flowertrail.png":"textures/flowertrail.png","foggy_birds.png":"textures/foggy_birds.png","foil.png":"textures/foil.png","frenchstucco.png":"textures/frenchstucco.png","furley_bg.png":"textures/furley_bg.png","gold_scale.png":"textures/gold_scale.png","gplaypattern.png":"textures/gplaypattern.png","gradient_squares.png":"textures/gradient_squares.png","graphy.png":"textures/graphy.png","gray_jean.png":"textures/gray_jean.png","gray_sand.png":"textures/gray_sand.png","green-fibers.png":"textures/green-fibers.png","green_dust_scratch.png":"textures/green_dust_scratch.png","green_gobbler.png":"textures/green_gobbler.png","grey.png":"textures/grey.png","grey_sandbag.png":"textures/grey_sandbag.png","grey_wash_wall.png":"textures/grey_wash_wall.png","greyfloral.png":"textures/greyfloral.png","grid.png":"textures/grid.png","grid_noise.png":"textures/grid_noise.png","gridme.png":"textures/gridme.png","grilled.png":"textures/grilled.png","groovepaper.png":"textures/groovepaper.png","grunge_wall.png":"textures/grunge_wall.png","gun_metal.png":"textures/gun_metal.png","handmadepaper.png":"textures/handmadepaper.png","hexabump.png":"textures/hexabump.png","hexellence.png":"textures/hexellence.png","hixs_pattern_evolution.png":"textures/hixs_pattern_evolution.png","honey_im_subtle.png":"textures/honey_im_subtle.png","husk.png":"textures/husk.png","ice_age.png":"textures/ice_age.png","inflicted.png":"textures/inflicted.png","irongrip.png":"textures/irongrip.png","kindajean.png":"textures/kindajean.png","knitted-netting.png":"textures/knitted-netting.png","knitting250px.png":"textures/knitting250px.png","kuji.png":"textures/kuji.png","large_leather.png":"textures/large_leather.png","leather_1.png":"textures/leather_1.png","lghtmesh.png":"textures/lghtmesh.png","light_alu.png":"textures/light_alu.png","light_checkered_tiles.png":"textures/light_checkered_tiles.png","light_grey_floral_motif.png":"textures/light_grey_floral_motif.png","light_honeycomb.png":"textures/light_honeycomb.png","light_noise_diagonal.png":"textures/light_noise_diagonal.png","light_toast.png":"textures/light_toast.png","light_wool.png":"textures/light_wool.png","lightpaperfibers.png":"textures/lightpaperfibers.png","lil_fiber.png":"textures/lil_fiber.png","lined_paper.png":"textures/lined_paper.png","linedpaper.png":"textures/linedpaper.png","linen.png":"textures/linen.png","little_pluses.png":"textures/little_pluses.png","little_triangles.png":"textures/little_triangles.png","littleknobs.png":"textures/littleknobs.png","low_contrast_linen.png":"textures/low_contrast_linen.png","lyonnette.png":"textures/lyonnette.png","merely_cubed.png":"textures/merely_cubed.png","micro_carbon.png":"textures/micro_carbon.png","mirrored_squares.png":"textures/mirrored_squares.png","mochaGrunge.png":"textures/mochaGrunge.png","mooning.png":"textures/mooning.png","moulin.png":"textures/moulin.png","nami.png":"textures/nami.png","nasty_fabric.png":"textures/nasty_fabric.png","natural_paper.png":"textures/natural_paper.png","navy_blue.png":"textures/navy_blue.png","nistri.png":"textures/nistri.png","noise_lines.png":"textures/noise_lines.png","noise_pattern_with_crosslines.png":"textures/noise_pattern_with_crosslines.png","noisy.png":"textures/noisy.png","noisy_grid.png":"textures/noisy_grid.png","noisy_net.png":"textures/noisy_net.png","norwegian_rose.png":"textures/norwegian_rose.png","office.png":"textures/office.png","old_mathematics.png":"textures/old_mathematics.png","old_wall.png":"textures/old_wall.png","otis_redding.png":"textures/otis_redding.png","outlets.png":"textures/outlets.png","p1.png":"textures/p1.png","p2.png":"textures/p2.png","p4.png":"textures/p4.png","p5.png":"textures/p5.png","p6.png":"textures/p6.png","padded.png":"textures/padded.png","paper.png":"textures/paper.png","paper_1.png":"textures/paper_1.png","paper_2.png":"textures/paper_2.png","paper_3.png":"textures/paper_3.png","paper_fibers.png":"textures/paper_fibers.png","paven.png":"textures/paven.png","perforated_white_leather.png":"textures/perforated_white_leather.png","pineapplecut.png":"textures/pineapplecut.png","pinstripe.png":"textures/pinstripe.png","pinstriped_suit.png":"textures/pinstriped_suit.png","plaid.png":"textures/plaid.png","polaroid.png":"textures/polaroid.png","polonez_car.png":"textures/polonez_car.png","polyester_lite.png":"textures/polyester_lite.png","pool_table.png":"textures/pool_table.png","project_papper.png":"textures/project_papper.png","ps_neutral.png":"textures/ps_neutral.png","psychedelic_pattern.png":"textures/psychedelic_pattern.png","purty_wood.png":"textures/purty_wood.png","pw_maze_black.png":"textures/pw_maze_black.png","pw_maze_white.png":"textures/pw_maze_white.png","pw_pattern.png":"textures/pw_pattern.png","px_by_Gre3g.png":"textures/px_by_Gre3g.png","pyramid.png":"textures/pyramid.png","quilt.png":"textures/quilt.png","random_grey_variations.png":"textures/random_grey_variations.png","ravenna.png":"textures/ravenna.png","real_cf.png":"textures/real_cf.png","rebel.png":"textures/rebel.png","redox_01.png":"textures/redox_01.png","redox_02.png":"textures/redox_02.png","reticular_tissue.png":"textures/reticular_tissue.png","retina_wood.png":"textures/retina_wood.png","retro_intro.png":"textures/retro_intro.png","ricepaper.png":"textures/ricepaper.png","ricepaper2.png":"textures/ricepaper2.png","rip_jobs.png":"textures/rip_jobs.png","robots.png":"textures/robots.png","rockywall.png":"textures/rockywall.png","rough_diagonal.png":"textures/rough_diagonal.png","roughcloth.png":"textures/roughcloth.png","rubber_grip.png":"textures/rubber_grip.png","satinweave.png":"textures/satinweave.png","scribble_light.png":"textures/scribble_light.png","shattered.png":"textures/shattered.png","shinecaro.png":"textures/shinecaro.png","shinedotted.png":"textures/shinedotted.png","shl.png":"textures/shl.png","silver_scales.png":"textures/silver_scales.png","simple_dashed.png":"textures/simple_dashed.png","skelatal_weave.png":"textures/skelatal_weave.png","skewed_print.png":"textures/skewed_print.png","skin_side_up.png":"textures/skin_side_up.png","slash_it.png":"textures/slash_it.png","small-crackle-bright.png":"textures/small-crackle-bright.png","small_tiles.png":"textures/small_tiles.png","smooth_wall.png":"textures/smooth_wall.png","sneaker_mesh_fabric.png":"textures/sneaker_mesh_fabric.png","snow.png":"textures/snow.png","soft_circle_scales.png":"textures/soft_circle_scales.png","soft_kill.png":"textures/soft_kill.png","soft_pad.png":"textures/soft_pad.png","soft_wallpaper.png":"textures/soft_wallpaper.png","solid.png":"textures/solid.png","squairy_light.png":"textures/squairy_light.png","square_bg.png":"textures/square_bg.png","squares.png":"textures/squares.png","stacked_circles.png":"textures/stacked_circles.png","starring.png":"textures/starring.png","stitched_wool.png":"textures/stitched_wool.png","strange_bullseyes.png":"textures/strange_bullseyes.png","straws.png":"textures/straws.png","stressed_linen.png":"textures/stressed_linen.png","striped_lens.png":"textures/striped_lens.png","struckaxiom.png":"textures/struckaxiom.png","stucco.png":"textures/stucco.png","subtle_carbon.png":"textures/subtle_carbon.png","subtle_dots.png":"textures/subtle_dots.png","subtle_freckles.png":"textures/subtle_freckles.png","subtle_grunge.png":"textures/subtle_grunge.png","subtle_orange_emboss.png":"textures/subtle_orange_emboss.png","subtle_stripes.png":"textures/subtle_stripes.png","subtle_surface.png":"textures/subtle_surface.png","subtle_white_feathers.png":"textures/subtle_white_feathers.png","subtle_zebra_3d.png":"textures/subtle_zebra_3d.png","subtlenet2.png":"textures/subtlenet2.png","swirl.png":"textures/swirl.png","tactile_noise.png":"textures/tactile_noise.png","tapestry_pattern.png":"textures/tapestry_pattern.png","tasky_pattern.png":"textures/tasky_pattern.png","tex2res1.png":"textures/tex2res1.png","tex2res2.png":"textures/tex2res2.png","tex2res3.png":"textures/tex2res3.png","tex2res4.png":"textures/tex2res4.png","tex2res5.png":"textures/tex2res5.png","textured_paper.png":"textures/textured_paper.png","textured_stripes.png":"textures/textured_stripes.png","texturetastic_gray.png":"textures/texturetastic_gray.png","ticks.png":"textures/ticks.png","tileable_wood_texture.png":"textures/tileable_wood_texture.png","tiny_grid.png":"textures/tiny_grid.png","triangles.png":"textures/triangles.png","triangles_pattern.png":"textures/triangles_pattern.png","tweed.png":"textures/tweed.png","twinkle_twinkle.png":"textures/twinkle_twinkle.png","txture.png":"textures/txture.png","type.png":"textures/type.png","use_your_illusion.png":"textures/use_your_illusion.png","vaio_hard_edge.png":"textures/vaio_hard_edge.png","vertical_cloth.png":"textures/vertical_cloth.png","vichy.png":"textures/vichy.png","vintage_speckles.png":"textures/vintage_speckles.png","wall4.png":"textures/wall4.png","washi.png":"textures/washi.png","wavecut.png":"textures/wavecut.png","wavegrid.png":"textures/wavegrid.png","weave.png":"textures/weave.png","white_bed_sheet.png":"textures/white_bed_sheet.png","white_brick_wall.png":"textures/white_brick_wall.png","white_carbon.png":"textures/white_carbon.png","white_carbonfiber.png":"textures/white_carbonfiber.png","white_leather.png":"textures/white_leather.png","white_paperboard.png":"textures/white_paperboard.png","white_plaster.png":"textures/white_plaster.png","white_sand.png":"textures/white_sand.png","white_texture.png":"textures/white_texture.png","white_tiles.png":"textures/white_tiles.png","white_wall.png":"textures/white_wall.png","white_wall2.png":"textures/white_wall2.png","white_wall_hash.png":"textures/white_wall_hash.png","white_wave.png":"textures/white_wave.png","whitediamond.png":"textures/whitediamond.png","whitey.png":"textures/whitey.png","wide_rectangles.png":"textures/wide_rectangles.png","wild_oliva.png":"textures/wild_oliva.png","witewall_3.png":"textures/witewall_3.png","wood_1.jpg":"textures/wood_1.jpg","wood_1.png":"textures/wood_1.png","wood_pattern.png":"textures/wood_pattern.png","worn_dots.png":"textures/worn_dots.png","woven.png":"textures/woven.png","xv.png":"textures/xv.png","zigzag.png":"textures/zigzag.png"}